{
  "trips": [
    {
      "name": "Unbranded Cotton Salad",
      "id": 2
    },
    {
      "name": "Awesome Fresh Chair",
      "id": 3
    },
    {
      "name": "Recycled Concrete Mouse",
      "id": 4
    },
    {
      "name": "Japan",
      "id": 7
    },
    {
      "name": "Thunksgiving",
      "id": 10
    },
    {
      "name": "NYC",
      "id": 11
    }
  ],
  "luggages": [
    {
      "tripId": 3,
      "title": "Sleek Granite Tuna",
      "id": 7
    },
    {
      "tripId": 3,
      "title": "Refined Frozen Car",
      "id": 8
    },
    {
      "tripId": 2,
      "title": "Luxurious Concrete Sausages",
      "id": 11
    },
    {
      "tripId": 2,
      "title": "Hand Bag",
      "id": 14
    },
    {
      "tripId": 2,
      "title": "Pink Bag",
      "id": 15
    },
    {
      "parentId": 2,
      "name": "Orange Bag",
      "id": 16
    },
    {
      "parentId": 2,
      "name": "blue bag",
      "id": 17
    }
  ],
  "items": [
    {
      "entry": "Refined Granite Tuna",
      "id": 1
    },
    {
      "entry": "Luxurious Wooden Pizza",
      "id": 2
    },
    {
      "entry": "Ergonomic Plastic Ball",
      "id": 3
    },
    {
      "entry": "Rustic Soft Computer",
      "id": 4
    }
  ]
}